edynamics/__init__.py
EmpiricalDynamics-0.1.2.dist-info/METADATA
EmpiricalDynamics-0.1.2.dist-info/WHEEL
EmpiricalDynamics-0.1.2.dist-info/top_level.txt
EmpiricalDynamics-0.1.2.dist-info/RECORD
