Metadata-Version: 2.1
Name: EmpiricalDynamics
Version: 0.1.2
Summary: Modelling tools for nonlinear state space reconstruction analysis
Author: Patrick Mahon
Author-email: pmahon3@uwo.ca
